setup.py
docs/HISTORY.txt
docs/INSTALL.txt
docs/LICENSE.GPL
docs/LICENSE.txt
docs/README.txt
paab/__init__.py
paab.policy.egg-info/PKG-INFO
paab.policy.egg-info/SOURCES.txt
paab.policy.egg-info/dependency_links.txt
paab.policy.egg-info/entry_points.txt
paab.policy.egg-info/namespace_packages.txt
paab.policy.egg-info/not-zip-safe
paab.policy.egg-info/paster_plugins.txt
paab.policy.egg-info/requires.txt
paab.policy.egg-info/top_level.txt
paab/policy/__init__.py
paab/policy/configure.zcml
paab/policy/tests.py
paab/policy/version.txt
paab/policy/actions/__init__.py
paab/policy/actions/configure.zcml
paab/policy/actions/default.py
paab/policy/actions/display.py
paab/policy/exportimport/__init__.py
paab/policy/exportimport/setuphandlers.py
paab/policy/profiles/default/import_steps.xml
paab/policy/profiles/default/properties.xml
paab/policy/profiles/default/types/Document.xml
paab/policy/profiles/default/types/Event.xml
paab/policy/profiles/default/types/Folder.xml
paab/policy/profiles/default/types/Image.xml
paab/policy/profiles/default/types/Link.xml
paab/policy/profiles/default/types/News_Item.xml
paab/policy/profiles/default/types/Topic.xml
paab/policy/skins/paab_policy/blog_summary_view.pt
paab/policy/skins/paab_policy/blog_summary_view.pt.metadata
paab/policy/skins/paab_policy/getHowManyBlogItems.py
paab/policy/skins/paab_policy/getLastUpdate.py
paab/policy/skins/paab_policy/section_summary_view.pt
paab/policy/skins/paab_policy/section_summary_view.pt.metada
paab/policy/tests/__init__.py
paab/policy/tests/base.py
paab/policy/tests/test_setup.py
