Metadata-Version: 1.0
Name: paab.policy
Version: 0.2
Summary: paab policy product
Home-page: http://plone.org/products/paab
Author: Roberto Allende - menttes
Author-email: rover@menttes.com
License: GPL
Keywords: blog weblog ploneblog
Platform: UNKNOWN
Classifier: Framework :: Plone
Classifier: Framework :: Zope2
Classifier: Framework :: Zope3
Classifier: Programming Language :: Python
Classifier: Topic :: Software Development :: Libraries :: Python Modules
